mlflow_cloudflare_header_plugin/__init__.py
mlflow_cloudflare_header_plugin/cloudflare_auth_header_provider.py
mlflow_cloudflare_header_plugin-1.0.0.dist-info/METADATA
mlflow_cloudflare_header_plugin-1.0.0.dist-info/WHEEL
mlflow_cloudflare_header_plugin-1.0.0.dist-info/entry_points.txt
mlflow_cloudflare_header_plugin-1.0.0.dist-info/RECORD
