Metadata-Version: 2.1
Name: mlflow-cloudflare-header-plugin
Version: 1.0.0
Summary: MLFlow plugin that adds extra headers required for Cloudflare access to all outgoing MLFlow requests
License: MIT
Author: Maciej Blasiak
Author-email: maciej.blasiak@goflink.com
Requires-Python: >=3.9
Classifier: License :: OSI Approved :: MIT License
Classifier: Programming Language :: Python :: 3
Classifier: Programming Language :: Python :: 3.9
Classifier: Programming Language :: Python :: 3.10
Classifier: Programming Language :: Python :: 3.11
Classifier: Programming Language :: Python :: 3.12
Requires-Dist: mlflow (>=2.9.0)
